trr_ds_core/__init__.py
trr_ds_core-0.0.0a0.dist-info/WHEEL
trr_ds_core-0.0.0a0.dist-info/METADATA
trr_ds_core-0.0.0a0.dist-info/RECORD
