Metadata-Version: 2.1
Name: trr-ds-core
Version: 0.0.0a0
Summary: dummy trr-ds-core
Author: Scyther
Requires-Python: >=3.9,<3.10
Classifier: Programming Language :: Python :: 3
Classifier: Programming Language :: Python :: 3.9
